burger_shop_reminder/__init__.py
burger_shop_reminder/bar_gar.py
burger_shop_reminder-1.0.0.dist-info/LICENSE
burger_shop_reminder-1.0.0.dist-info/METADATA
burger_shop_reminder-1.0.0.dist-info/WHEEL
burger_shop_reminder-1.0.0.dist-info/entry_points.txt
burger_shop_reminder-1.0.0.dist-info/top_level.txt
burger_shop_reminder-1.0.0.dist-info/RECORD
