Metadata-Version: 2.1
Name: burger-shop-reminder
Version: 1.0.0
Summary: A daily reminder for a random burger shop with images
Home-page: https://github.com/yanoyuuki7/burger_shop_reminder.git
Author: YUKI YANO
Author-email: s2222036@stu.musashino-u.ac.jp
License: UNKNOWN
Platform: UNKNOWN
Classifier: Programming Language :: Python :: 3
Classifier: License :: OSI Approved :: MIT License
Classifier: Operating System :: OS Independent
Requires-Python: >=3.6
License-File: LICENSE
Requires-Dist: requests
Requires-Dist: Pillow
Requires-Dist: apscheduler
Requires-Dist: matplotlib
